.hgignore
.hgtags
.project
changelog
setup.py
jp_grapheme_alt.egg-info/PKG-INFO
jp_grapheme_alt.egg-info/SOURCES.txt
jp_grapheme_alt.egg-info/dependency_links.txt
jp_grapheme_alt.egg-info/requires.txt
jp_grapheme_alt.egg-info/top_level.txt
src/__init__.py
src/__version__.py
src/admin.py
src/confusion_model.py
src/grapheme_database.py
src/models.py
src/test_confusion_model.py
src/views.py
src/data/jyouyou__strokeEditDistance
src/data/jyouyou__yehAndLiRadical
src/data/jyouyou__yehAndLiRadicalKansuke