Metadata-Version: 1.0
Name: jp-grapheme-alt
Version: 0.1.2
Summary: Probabilistic misrecognition models for Japanese kanji.
Home-page: http://bitbucket.org/lars512/jp-grapheme-alt/
Author: Lars Yencken
Author-email: lljy@csse.unimelb.edu.au
License: BSD
Platform: UNKNOWN
